tiny_markdown_server/__init__.py
tiny_markdown_server/tiny_markdown_server.py
tiny_markdown_server-0.1.0.dist-info/entry_points.txt
tiny_markdown_server-0.1.0.dist-info/LICENSE
tiny_markdown_server-0.1.0.dist-info/WHEEL
tiny_markdown_server-0.1.0.dist-info/METADATA
tiny_markdown_server-0.1.0.dist-info/RECORD
